uniconpy/__init__.py
uniconpy/massa.py
uniconpy/temperatura.py
uniconpy/volume.py
uniconpy-1.1.0.dist-info/METADATA
uniconpy-1.1.0.dist-info/WHEEL
uniconpy-1.1.0.dist-info/licenses/LICENSE.txt
uniconpy-1.1.0.dist-info/RECORD
