Metadata-Version: 2.4
Name: uniconpy
Version: 1.1.0
Summary: Pacote para a conversão de unidades de massa, temperatura e volume
Project-URL: Homepage, https://github.com/seu_pacote
Project-URL: Documentation, https://github.com/seu_pacote/docs
Author-email: matcomp <projeto@matcomp.com.br>
License: MIT License
License-File: LICENSE.txt
Keywords: conversão,massa,temperatura
Requires-Python: >=3.8
